wbg/organization/__init__.py
wbg/organization/aa-staff.yaml
wbg/organization/aa.py
wbg/organization/country.py
wbg/organization/create_index.sql
wbg/organization/edc.py
wbg/organization/hierarchy.py
wbg/organization/jobs.py
wbg/organization/py.typed
wbg/organization/query.py
wbg/organization/scripts/update_staff.py
wbg/organization/tests/__init__.py
wbg/organization/tests/test_aa.py
wbg/organization/tests/test_query.py
wbg/organization/tests/data/aa.csv
wbg/organization/tests/data/raw.csv
wbg_organization-1.0.0.dist-info/METADATA
wbg_organization-1.0.0.dist-info/WHEEL
wbg_organization-1.0.0.dist-info/top_level.txt
wbg_organization-1.0.0.dist-info/RECORD
