Metadata-Version: 2.1
Name: wbg-organization
Version: 1.0.0
Requires-Python: >=3.10
Requires-Dist: wbg-sharepoint <2.0.0,>=1.0.0
Requires-Dist: networkx
Requires-Dist: nltk
Requires-Dist: numpy
Requires-Dist: pandas
Requires-Dist: pyyaml
Requires-Dist: requests
Requires-Dist: termcolor
Requires-Dist: tqdm
